LICENSE.txt
README.md
setup.py
PySolveX.egg-info/PKG-INFO
PySolveX.egg-info/SOURCES.txt
PySolveX.egg-info/dependency_links.txt
PySolveX.egg-info/requires.txt
PySolveX.egg-info/top_level.txt
PysolveX/__init__.py
PysolveX/reCAPTCHA_V2.py
PysolveX/reCAPTCHA_V3.py