Metadata-Version: 2.1
Name: PySolveX
Version: 0.0.1
Summary: Bypassing reCaptcha V3, V2 by Selenium.
Author: VIRUS
Keywords: Bypass reCaptcha V3,Bypass-reCaptcha-V3,Bypass reCaptcha,Bypass-reCaptcha,Bypass reCaptcha V2,Bypass-reCaptcha-V2,Solve-reCaptcha-V2,Google reCaptcha,Google-reCaptcha
Classifier: Development Status :: 4 - Beta
Classifier: Intended Audience :: Developers
Classifier: License :: OSI Approved :: MIT License
Classifier: Topic :: Software Development :: Libraries :: Python Modules
Classifier: Programming Language :: Python :: 3.7
Classifier: Programming Language :: Python :: 3.8
Requires-Python: >=3.7
License-File: LICENSE.txt
